LICENSE
text_explore/__init__.py
text_explore/counts.py
text_explore/readability.py
text_explore/utils.py
text_explore-0.0.2.dist-info/LICENSE
text_explore-0.0.2.dist-info/WHEEL
text_explore-0.0.2.dist-info/METADATA
text_explore-0.0.2.dist-info/RECORD
