Metadata-Version: 2.1
Name: text-explore
Version: 0.0.2
Summary: A Python Package to perform Exploratory Data Analysis on Text Data.
Home-page: https://github.com/temmyzeus/text_explore
License: MIT
Author: Temiloluwa Awoyele
Author-email: awoyeletemiloluwa@gmail.com
Requires-Python: >=3.7,<4.0
Classifier: License :: OSI Approved :: MIT License
Classifier: Programming Language :: Python :: 3
Classifier: Programming Language :: Python :: 3.10
Classifier: Programming Language :: Python :: 3.7
Classifier: Programming Language :: Python :: 3.8
Classifier: Programming Language :: Python :: 3.9
Requires-Dist: nltk (==3.6.6)
Project-URL: Repository, https://github.com/temmyzeus/text_explore
